google_services_account_tools-1.4.0.dist-info/licenses/LICENSE
tools/__init__.py
tools/tools.py
google_services_account_tools-1.4.0.dist-info/METADATA
google_services_account_tools-1.4.0.dist-info/WHEEL
google_services_account_tools-1.4.0.dist-info/top_level.txt
google_services_account_tools-1.4.0.dist-info/RECORD
